cg3d_maya_core-0.7.0.dist-info/licenses/LICENSE
cg3dguru/__init__.py
cg3dguru/animation/__init__.py
cg3dguru/animation/fbx.py
cg3dguru/animation/hik.py
cg3dguru/modeling/__init__.py
cg3dguru/modeling/fingers.py
cg3dguru/modeling/fingers.ui
cg3dguru/rigging/__init__.py
cg3dguru/rigging/stretchy_spline.py
cg3dguru/udata/__init__.py
cg3dguru/udata/core.py
cg3dguru/udata/editor.py
cg3dguru/udata/user_data.ui
cg3dguru/ui/__init__.py
cg3dguru/ui/core.py
cg3dguru/utils/__init__.py
cg3dguru/utils/core.py
cg3dguru/utils/drop_installer.py
cg3dguru/utils/math.py
cg3dguru/utils/menu_maker.py
cg3dguru/utils/modeling.py
cg3d_maya_core-0.7.0.dist-info/METADATA
cg3d_maya_core-0.7.0.dist-info/WHEEL
cg3d_maya_core-0.7.0.dist-info/top_level.txt
cg3d_maya_core-0.7.0.dist-info/RECORD
