Metadata-Version: 2.4
Name: cg3d-maya-core
Version: 0.7.0
Summary: A collection of Maya functions and classes that can easily be pulled into other projects/modules
Author-email: Nathaniel A <developer@3dcg.guru>
Project-URL: Homepage, https://github.com/Nathanieljla/cg3d-maya-core
Classifier: Programming Language :: Python :: 3
Classifier: Operating System :: OS Independent
Requires-Python: >=3.4
License-File: LICENSE
Requires-Dist: pymel>=1.3
Dynamic: license-file
